pikrellcam_python/__init__.py
pikrellcam_python/pikrellcam_python.py
pikrellcam_python-0.1.1.dist-info/AUTHORS.rst
pikrellcam_python-0.1.1.dist-info/LICENSE
pikrellcam_python-0.1.1.dist-info/METADATA
pikrellcam_python-0.1.1.dist-info/WHEEL
pikrellcam_python-0.1.1.dist-info/top_level.txt
pikrellcam_python-0.1.1.dist-info/RECORD
