Metadata-Version: 2.1
Name: pikrellcam-python
Version: 0.1.1
Summary: A Python3, async interface for PiKrellCam http://billw2.github.io/pikre
Home-page: https://github.com/lekobob/pikrellcam_python
Author: Joshua Hahn
Author-email: josh.w.hahn@gmail.com
License: MIT license
Keywords: pikrellcam_python
Platform: UNKNOWN
Classifier: Development Status :: 2 - Pre-Alpha
Classifier: Intended Audience :: Developers
Classifier: License :: OSI Approved :: MIT License
Classifier: Natural Language :: English
Classifier: Programming Language :: Python :: 3
Classifier: Programming Language :: Python :: 3.4
Classifier: Programming Language :: Python :: 3.5
Classifier: Programming Language :: Python :: 3.6
Classifier: Programming Language :: Python :: 3.7
Requires-Dist: aiohttp
